{
  "page_info": {
    "page_num": 0,
    "width": 1191.0,
    "height": 842.0
  },
  "continuous_beams": [
    {
      "parent_id": 0,
      "parent_bbox": [
        54.75,
        28.25,
        560.25,
        118.75
      ],
      "titles": [
        {
          "text": "10F B3-2",
          "bbox": [
            188.19,
            109.6,
            270.82,
            118.21
          ]
        },
        {
          "text": "10F CB3-3",
          "bbox": [
            425.13,
            109.6,
            513.08,
            118.21
          ]
        },
        {
          "text": "10F B3-2",
          "bbox": [
            194.09,
            109.96,
            275.9,
            118.17
          ]
        },
        {
          "text": "10F CB3-3",
          "bbox": [
            430.47,
            109.96,
            517.9,
            118.17
          ]
        }
      ],
      "single_spans": [
        [
          54.75,
          28.25,
          560.25,
          118.75
        ]
      ]
    },
    {
      "parent_id": 1,
      "parent_bbox": [
        61.75,
        129.0,
        560.5,
        220.5
      ],
      "titles": [
        {
          "text": "9F B3-2",
          "bbox": [
            220.17,
            211.32,
            250.77,
            216.68
          ]
        },
        {
          "text": "9F CR3-3",
          "bbox": [
            459.78,
            211.36,
            490.69,
            216.72
          ]
        },
        {
          "text": "9F B3-2",
          "bbox": [
            197.25,
            211.0,
            273.5,
            219.5
          ]
        },
        {
          "text": "9F CB3-3",
          "bbox": [
            433.25,
            210.0,
            516.25,
            219.75
          ]
        },
        {
          "text": "9F B3-2",
          "bbox": [
            192.02,
            210.86,
            268.74,
            219.06
          ]
        },
        {
          "text": "9F CB3-3",
          "bbox": [
            428.12,
            210.86,
            509.85,
            219.06
          ]
        }
      ],
      "single_spans": [
        [
          61.75,
          129.0,
          560.5,
          220.5
        ]
      ]
    },
    {
      "parent_id": 2,
      "parent_bbox": [
        54.75,
        230.25,
        560.5,
        321.25
      ],
      "titles": [
        {
          "text": "8F B3-2",
          "bbox": [
            215.0,
            312.13,
            245.68,
            317.8
          ]
        },
        {
          "text": "8F CB3-3",
          "bbox": [
            454.74,
            312.37,
            485.42,
            317.72
          ]
        },
        {
          "text": "8F B3-2",
          "bbox": [
            215.31,
            311.75,
            255.81,
            320.5
          ]
        },
        {
          "text": "8F CB3-3",
          "bbox": [
            454.78,
            311.78,
            499.78,
            320.28
          ]
        },
        {
          "text": "8F B3-2",
          "bbox": [
            191.0,
            310.73,
            268.63,
            320.63
          ]
        },
        {
          "text": "8F CB3-3",
          "bbox": [
            428.26,
            311.66,
            510.58,
            320.01
          ]
        }
      ],
      "single_spans": [
        [
          54.75,
          230.25,
          560.5,
          321.25
        ]
      ]
    },
    {
      "parent_id": 3,
      "parent_bbox": [
        54.75,
        331.0,
        560.5,
        422.5
      ],
      "titles": [
        {
          "text": "7F B3-2",
          "bbox": [
            216.88,
            412.72,
            256.62,
            421.22
          ]
        },
        {
          "text": "7F B3-2",
          "bbox": [
            191.32,
            412.75,
            268.94,
            421.1
          ]
        },
        {
          "text": "7F CB3-3",
          "bbox": [
            427.32,
            411.83,
            511.21,
            421.72
          ]
        },
        {
          "text": "7F CB3-3",
          "bbox": [
            433.0,
            412.75,
            516.25,
            421.75
          ]
        },
        {
          "text": "7F B3-2",
          "bbox": [
            191.71,
            412.96,
            268.74,
            421.17
          ]
        },
        {
          "text": "7F CB3-3",
          "bbox": [
            428.12,
            412.64,
            509.85,
            421.17
          ]
        }
      ],
      "single_spans": [
        [
          54.75,
          331.0,
          560.5,
          422.5
        ]
      ]
    },
    {
      "parent_id": 4,
      "parent_bbox": [
        590.0,
        129.0,
        1089.0,
        220.25
      ],
      "titles": [
        {
          "text": "9F CB3-4",
          "bbox": [
            661.44,
            211.12,
            692.97,
            216.8
          ]
        },
        {
          "text": "9F B3-5",
          "bbox": [
            900.49,
            211.36,
            931.39,
            216.72
          ]
        },
        {
          "text": "9F B3-5",
          "bbox": [
            877.5,
            211.0,
            954.5,
            219.5
          ]
        },
        {
          "text": "9F CB3-4",
          "bbox": [
            635.5,
            211.0,
            718.0,
            219.5
          ]
        },
        {
          "text": "9F CB3-4",
          "bbox": [
            635.43,
            210.86,
            717.5,
            219.06
          ]
        },
        {
          "text": "9F B3-5",
          "bbox": [
            877.22,
            210.86,
            954.23,
            219.06
          ]
        }
      ],
      "single_spans": [
        [
          590.0,
          129.0,
          1089.0,
          220.25
        ]
      ]
    },
    {
      "parent_id": 5,
      "parent_bbox": [
        590.0,
        230.25,
        1095.5,
        321.25
      ],
      "titles": [
        {
          "text": "8F CB3-4",
          "bbox": [
            661.61,
            312.09,
            692.86,
            317.76
          ]
        },
        {
          "text": "8F B3-5",
          "bbox": [
            900.57,
            312.09,
            931.19,
            317.76
          ]
        },
        {
          "text": "8F B3-5",
          "bbox": [
            897.56,
            311.75,
            937.31,
            320.5
          ]
        },
        {
          "text": "8F CB3-4",
          "bbox": [
            635.25,
            311.5,
            717.75,
            320.5
          ]
        },
        {
          "text": "8F CB3-4",
          "bbox": [
            634.8,
            310.73,
            717.81,
            320.63
          ]
        },
        {
          "text": "8F B3-5",
          "bbox": [
            876.58,
            311.35,
            953.92,
            320.63
          ]
        }
      ],
      "single_spans": [
        [
          590.0,
          230.25,
          1095.5,
          321.25
        ]
      ]
    },
    {
      "parent_id": 6,
      "parent_bbox": [
        590.0,
        331.0,
        1095.5,
        422.5
      ],
      "titles": [
        {
          "text": "7F B3-5",
          "bbox": [
            897.59,
            412.72,
            936.84,
            421.22
          ]
        },
        {
          "text": "7F CB3-4",
          "bbox": [
            634.48,
            411.83,
            718.13,
            421.72
          ]
        },
        {
          "text": "7F B3-5",
          "bbox": [
            876.9,
            412.75,
            953.92,
            421.1
          ]
        },
        {
          "text": "7F CB3-4",
          "bbox": [
            635.0,
            412.75,
            718.25,
            421.75
          ]
        },
        {
          "text": "7F CB3-4",
          "bbox": [
            635.43,
            412.96,
            717.81,
            421.17
          ]
        },
        {
          "text": "7F B3-5",
          "bbox": [
            877.22,
            412.64,
            954.23,
            420.85
          ]
        }
      ],
      "single_spans": [
        [
          590.0,
          331.0,
          1095.5,
          422.5
        ]
      ]
    },
    {
      "parent_id": 7,
      "parent_bbox": [
        54.75,
        432.0,
        560.5,
        523.25
      ],
      "titles": [
        {
          "text": "6F B3-2",
          "bbox": [
            215.0,
            514.04,
            245.68,
            519.72
          ]
        },
        {
          "text": "6F CB3-3",
          "bbox": [
            454.48,
            514.08,
            485.48,
            519.76
          ]
        },
        {
          "text": "6F B3-2",
          "bbox": [
            196.75,
            513.5,
            274.25,
            522.5
          ]
        },
        {
          "text": "6F CB3-3",
          "bbox": [
            454.94,
            514.25,
            499.94,
            521.75
          ]
        },
        {
          "text": "6F B3-2",
          "bbox": [
            191.94,
            513.77,
            268.32,
            522.18
          ]
        },
        {
          "text": "6F CB3-3",
          "bbox": [
            428.26,
            513.46,
            510.27,
            521.87
          ]
        }
      ],
      "single_spans": [
        [
          54.75,
          432.0,
          560.5,
          523.25
        ]
      ]
    },
    {
      "parent_id": 8,
      "parent_bbox": [
        54.75,
        533.0,
        560.5,
        624.25
      ],
      "titles": [
        {
          "text": "5F B3-2",
          "bbox": [
            196.75,
            614.5,
            273.75,
            622.75
          ]
        },
        {
          "text": "5F B3-2",
          "bbox": [
            191.63,
            614.69,
            268.32,
            623.1
          ]
        },
        {
          "text": "5F CB3-3",
          "bbox": [
            427.95,
            614.38,
            510.27,
            622.78
          ]
        },
        {
          "text": "5F CB3-3",
          "bbox": [
            432.75,
            614.0,
            516.5,
            623.5
          ]
        }
      ],
      "single_spans": [
        [
          54.75,
          533.0,
          560.5,
          624.25
        ]
      ]
    },
    {
      "parent_id": 9,
      "parent_bbox": [
        590.0,
        432.0,
        1095.5,
        523.25
      ],
      "titles": [
        {
          "text": "6F CB3-4",
          "bbox": [
            661.39,
            514.08,
            692.95,
            519.76
          ]
        },
        {
          "text": "6F B3-5",
          "bbox": [
            900.57,
            514.08,
            931.19,
            519.76
          ]
        },
        {
          "text": "6F B3-5",
          "bbox": [
            877.25,
            513.5,
            954.5,
            522.5
          ]
        },
        {
          "text": "6F CB3-4",
          "bbox": [
            635.5,
            513.75,
            717.5,
            521.75
          ]
        },
        {
          "text": "6F CB3-4",
          "bbox": [
            635.74,
            513.62,
            717.5,
            521.95
          ]
        },
        {
          "text": "6F B3-5",
          "bbox": [
            877.22,
            513.62,
            953.6,
            521.95
          ]
        }
      ],
      "single_spans": [
        [
          590.0,
          432.0,
          1095.5,
          523.25
        ]
      ]
    },
    {
      "parent_id": 10,
      "parent_bbox": [
        590.0,
        533.0,
        1095.5,
        623.75
      ],
      "titles": [
        {
          "text": "5F B3-5",
          "bbox": [
            877.0,
            614.75,
            954.25,
            623.0
          ]
        },
        {
          "text": "5F CB3-4",
          "bbox": [
            635.43,
            614.75,
            717.5,
            623.08
          ]
        },
        {
          "text": "5F B3-5",
          "bbox": [
            876.9,
            614.75,
            954.23,
            623.08
          ]
        },
        {
          "text": "5F CB3-4",
          "bbox": [
            635.75,
            615.0,
            718.25,
            623.0
          ]
        }
      ],
      "single_spans": [
        [
          590.0,
          533.0,
          1095.5,
          623.75
        ]
      ]
    },
    {
      "parent_id": 11,
      "parent_bbox": [
        590.0,
        28.25,
        1095.5,
        118.75
      ],
      "titles": [
        {
          "text": "10F CB3-4",
          "bbox": [
            632.27,
            109.6,
            720.34,
            118.21
          ]
        },
        {
          "text": "10F B3-5",
          "bbox": [
            874.06,
            109.6,
            956.13,
            118.21
          ]
        },
        {
          "text": "10F CB3-4",
          "bbox": [
            632.38,
            109.96,
            719.77,
            118.17
          ]
        },
        {
          "text": "10F B3-5",
          "bbox": [
            874.27,
            109.96,
            956.67,
            118.17
          ]
        }
      ],
      "single_spans": [
        [
          590.0,
          28.25,
          1095.5,
          118.75
        ]
      ]
    }
  ]
}